bin/auto_resolver.py
bin/resolver.py
migration_test/manage.py
migration_test/demo/__init__.py
migration_test/demo/admin.py
migration_test/demo/apps.py
migration_test/demo/models.py
migration_test/demo/tests.py
migration_test/demo/views.py
migration_test/demo/migrations/__init__.py
migration_test/migration_test/__init__.py
migration_test/migration_test/asgi.py
migration_test/migration_test/settings.py
migration_test/migration_test/urls.py
migration_test/migration_test/wsgi.py
django_migration_resolver_hook-0.2.8.dist-info/LICENSE
django_migration_resolver_hook-0.2.8.dist-info/METADATA
django_migration_resolver_hook-0.2.8.dist-info/WHEEL
django_migration_resolver_hook-0.2.8.dist-info/entry_points.txt
django_migration_resolver_hook-0.2.8.dist-info/top_level.txt
django_migration_resolver_hook-0.2.8.dist-info/RECORD
