Metadata-Version: 2.1
Name: django-migration-resolver-hook
Version: 0.2.8
Summary: Resolve migration conflicts.
Home-page: https://github.com/jackton1/django-migration-resolver-hook.git
Author: Tonye Jack
Author-email: jtonye@ymail.com
Maintainer: Tonye Jack
Maintainer-email: jtonye@ymail.com
License: MIT
Keywords: django,django migration,django migration resolver,django migration node conflict resolver
Platform: UNKNOWN
Classifier: Development Status :: 2 - Pre-Alpha
Classifier: Intended Audience :: Developers
Classifier: License :: OSI Approved :: MIT License
Classifier: Natural Language :: English
Classifier: Topic :: Internet :: WWW/HTTP
Classifier: Operating System :: OS Independent
Classifier: Programming Language :: Python :: 3.6
Classifier: Programming Language :: Python :: 3.7
Classifier: Programming Language :: Python :: Implementation :: CPython
Classifier: Programming Language :: Python :: Implementation :: PyPy
Classifier: Framework :: Django :: 1.11
Classifier: Framework :: Django :: 2.0
Classifier: Framework :: Django :: 2.1
Classifier: Framework :: Django :: 2.2
Requires-Python: >=3.6
Requires-Dist: django (>=1.11)
Provides-Extra: deploy
Requires-Dist: bump2version (==1.0.1) ; extra == 'deploy'
Requires-Dist: readme-renderer[md] ; extra == 'deploy'
Requires-Dist: twine (==3.4.1) ; extra == 'deploy'
Provides-Extra: development
Requires-Dist: pip-tools (==6.0.1) ; extra == 'development'
